setup.py
GenomeBrowser/__init__.py
GenomeBrowser.egg-info/PKG-INFO
GenomeBrowser.egg-info/SOURCES.txt
GenomeBrowser.egg-info/dependency_links.txt
GenomeBrowser.egg-info/requires.txt
GenomeBrowser.egg-info/top_level.txt
GenomeBrowser/Classes/DrawDataTracks.py
GenomeBrowser/Classes/DrawFeatureTracks.py
GenomeBrowser/Classes/__init__.py